rackio_opcua/__init__.py
rackio_opcua/_singleton.py
rackio_opcua/core.py
rackio_opcua/decorator.py
rackio_opcua/device.py
rackio_opcua/folder.py
rackio_opcua/updater.py
rackio_opcua/worker.py
RackioOPC_UA-0.7.dist-info/LICENSE
RackioOPC_UA-0.7.dist-info/METADATA
RackioOPC_UA-0.7.dist-info/WHEEL
RackioOPC_UA-0.7.dist-info/top_level.txt
RackioOPC_UA-0.7.dist-info/RECORD
