Metadata-Version: 2.1
Name: RackioOPC-UA
Version: 0.7
Summary: A Rackio extension to add a OPC-UA support
Home-page: https://github.com/rack-io/rackio-opc-ua
Author: Nelson Carrasquel
Author-email: rackio.framework@outlook.com
License: MIT
Platform: UNKNOWN
Classifier: Programming Language :: Python :: 3
Classifier: License :: OSI Approved :: MIT License
Classifier: Operating System :: OS Independent
Requires-Dist: opcua
